edf_carbon_server/__init__.py
edf_carbon_server/__version__.py
edf_carbon_server/config.py
edf_carbon_server/main.py
edf_carbon_server/pubsub.py
edf_carbon_server/storage.py
edf_carbon_server/synchronizer.py
edf_carbon_server/api/__init__.py
edf_carbon_server/api/case.py
edf_carbon_server/api/helper.py
edf_carbon_server-2.0.0.dist-info/licenses/LICENSE
edf_carbon_server-2.0.0.dist-info/METADATA
edf_carbon_server-2.0.0.dist-info/WHEEL
edf_carbon_server-2.0.0.dist-info/entry_points.txt
edf_carbon_server-2.0.0.dist-info/top_level.txt
edf_carbon_server-2.0.0.dist-info/RECORD
