Metadata-Version: 2.4
Name: edf-carbon-server
Version: 2.0.0
Summary: EDF Carbon Server
Author-email: CERT-EDF <cert@edf.fr>
License-Expression: MIT
Project-URL: Homepage, https://github.com/cert-edf/carbon
Project-URL: Repository, https://github.com/cert-edf/carbon
Project-URL: Bug Tracker, https://github.com/cert-edf/carbon/issues
Keywords: edf,carbon,server
Classifier: Development Status :: 5 - Production/Stable
Classifier: Intended Audience :: Developers
Classifier: Operating System :: POSIX :: Linux
Classifier: Programming Language :: Python :: 3
Classifier: Programming Language :: Python :: 3 :: Only
Classifier: Topic :: Utilities
Classifier: Topic :: Security
Requires-Python: >=3.12
License-File: LICENSE
Requires-Dist: edf-carbon-core~=2.0
Requires-Dist: aiosqlite~=0.20
Dynamic: license-file
